elegantpy/__init__.py
elegantpy/classes.py
elegantpy/sdds.py
ElegantPy-1.0rc0.dev1.dist-info/DESCRIPTION.rst
ElegantPy-1.0rc0.dev1.dist-info/METADATA
ElegantPy-1.0rc0.dev1.dist-info/metadata.json
ElegantPy-1.0rc0.dev1.dist-info/RECORD
ElegantPy-1.0rc0.dev1.dist-info/top_level.txt
ElegantPy-1.0rc0.dev1.dist-info/WHEEL
