Metadata-Version: 2.0
Name: ElegantPy
Version: 1.0rc0.dev1
Summary: More Pythonic wrapper for Elegant
Home-page: https://github.com/joelfrederico/ElegantPy
Author: Joel Frederico, SLAC National Accelerator Laboratory
Author-email: joelfred@slac.stanford.edu
License: MIT
Keywords: analysis numpy scipy matplotlib
Platform: UNKNOWN
Classifier: Development Status :: 4 - Beta
Classifier: Intended Audience :: Science/Research
Classifier: Topic :: Scientific/Engineering :: Information Analysis
Classifier: License :: OSI Approved :: MIT License
Classifier: Programming Language :: Python :: 2
Classifier: Programming Language :: Python :: 3
Classifier: Programming Language :: Python :: 3.4
